{
  "status": "done",
  "assets": {
    "main.js": {
      "name": "main.js",
      "path": "/Users/stevehiehn/SignalsAndSorceryWeb/static/dist/main.js",
      "publicPath": "/static/dist/main.js"
    },
    "main.3d2cfb800fe44cbd1f5b.hot-update.js": {
      "name": "main.3d2cfb800fe44cbd1f5b.hot-update.js",
      "path": "/Users/stevehiehn/SignalsAndSorceryWeb/static/dist/main.3d2cfb800fe44cbd1f5b.hot-update.js",
      "publicPath": "/static/dist/main.3d2cfb800fe44cbd1f5b.hot-update.js"
    },
    "main.3d2cfb800fe44cbd1f5b.hot-update.json": {
      "name": "main.3d2cfb800fe44cbd1f5b.hot-update.json",
      "path": "/Users/stevehiehn/SignalsAndSorceryWeb/static/dist/main.3d2cfb800fe44cbd1f5b.hot-update.json",
      "publicPath": "/static/dist/main.3d2cfb800fe44cbd1f5b.hot-update.json"
    },
    "main.454570333dd7a92c1c5d.hot-update.js": {
      "name": "main.454570333dd7a92c1c5d.hot-update.js",
      "path": "/Users/stevehiehn/SignalsAndSorceryWeb/static/dist/main.454570333dd7a92c1c5d.hot-update.js",
      "publicPath": "/static/dist/main.454570333dd7a92c1c5d.hot-update.js"
    },
    "main.454570333dd7a92c1c5d.hot-update.json": {
      "name": "main.454570333dd7a92c1c5d.hot-update.json",
      "path": "/Users/stevehiehn/SignalsAndSorceryWeb/static/dist/main.454570333dd7a92c1c5d.hot-update.json",
      "publicPath": "/static/dist/main.454570333dd7a92c1c5d.hot-update.json"
    },
    "main.da92bc9a1e4b7e958b53.hot-update.js": {
      "name": "main.da92bc9a1e4b7e958b53.hot-update.js",
      "path": "/Users/stevehiehn/SignalsAndSorceryWeb/static/dist/main.da92bc9a1e4b7e958b53.hot-update.js",
      "publicPath": "/static/dist/main.da92bc9a1e4b7e958b53.hot-update.js"
    },
    "main.da92bc9a1e4b7e958b53.hot-update.json": {
      "name": "main.da92bc9a1e4b7e958b53.hot-update.json",
      "path": "/Users/stevehiehn/SignalsAndSorceryWeb/static/dist/main.da92bc9a1e4b7e958b53.hot-update.json",
      "publicPath": "/static/dist/main.da92bc9a1e4b7e958b53.hot-update.json"
    },
    "main.5b47785bd839eb8781cb.hot-update.js": {
      "name": "main.5b47785bd839eb8781cb.hot-update.js",
      "path": "/Users/stevehiehn/SignalsAndSorceryWeb/static/dist/main.5b47785bd839eb8781cb.hot-update.js",
      "publicPath": "/static/dist/main.5b47785bd839eb8781cb.hot-update.js"
    },
    "main.5b47785bd839eb8781cb.hot-update.json": {
      "name": "main.5b47785bd839eb8781cb.hot-update.json",
      "path": "/Users/stevehiehn/SignalsAndSorceryWeb/static/dist/main.5b47785bd839eb8781cb.hot-update.json",
      "publicPath": "/static/dist/main.5b47785bd839eb8781cb.hot-update.json"
    },
    "main.6ff63dbfc698cabce48e.hot-update.js": {
      "name": "main.6ff63dbfc698cabce48e.hot-update.js",
      "path": "/Users/stevehiehn/SignalsAndSorceryWeb/static/dist/main.6ff63dbfc698cabce48e.hot-update.js",
      "publicPath": "/static/dist/main.6ff63dbfc698cabce48e.hot-update.js"
    },
    "main.6ff63dbfc698cabce48e.hot-update.json": {
      "name": "main.6ff63dbfc698cabce48e.hot-update.json",
      "path": "/Users/stevehiehn/SignalsAndSorceryWeb/static/dist/main.6ff63dbfc698cabce48e.hot-update.json",
      "publicPath": "/static/dist/main.6ff63dbfc698cabce48e.hot-update.json"
    },
    "main.11055dba3a7704e7e92c.hot-update.js": {
      "name": "main.11055dba3a7704e7e92c.hot-update.js",
      "path": "/Users/stevehiehn/SignalsAndSorceryWeb/static/dist/main.11055dba3a7704e7e92c.hot-update.js",
      "publicPath": "/static/dist/main.11055dba3a7704e7e92c.hot-update.js"
    },
    "main.11055dba3a7704e7e92c.hot-update.json": {
      "name": "main.11055dba3a7704e7e92c.hot-update.json",
      "path": "/Users/stevehiehn/SignalsAndSorceryWeb/static/dist/main.11055dba3a7704e7e92c.hot-update.json",
      "publicPath": "/static/dist/main.11055dba3a7704e7e92c.hot-update.json"
    },
    "main.9dae548f6ae0752c0a5a.hot-update.js": {
      "name": "main.9dae548f6ae0752c0a5a.hot-update.js",
      "path": "/Users/stevehiehn/SignalsAndSorceryWeb/static/dist/main.9dae548f6ae0752c0a5a.hot-update.js",
      "publicPath": "/static/dist/main.9dae548f6ae0752c0a5a.hot-update.js"
    },
    "main.9dae548f6ae0752c0a5a.hot-update.json": {
      "name": "main.9dae548f6ae0752c0a5a.hot-update.json",
      "path": "/Users/stevehiehn/SignalsAndSorceryWeb/static/dist/main.9dae548f6ae0752c0a5a.hot-update.json",
      "publicPath": "/static/dist/main.9dae548f6ae0752c0a5a.hot-update.json"
    },
    "main.41a4ecbac3d541d0d30a.hot-update.js": {
      "name": "main.41a4ecbac3d541d0d30a.hot-update.js",
      "path": "/Users/stevehiehn/SignalsAndSorceryWeb/static/dist/main.41a4ecbac3d541d0d30a.hot-update.js",
      "publicPath": "/static/dist/main.41a4ecbac3d541d0d30a.hot-update.js"
    },
    "main.41a4ecbac3d541d0d30a.hot-update.json": {
      "name": "main.41a4ecbac3d541d0d30a.hot-update.json",
      "path": "/Users/stevehiehn/SignalsAndSorceryWeb/static/dist/main.41a4ecbac3d541d0d30a.hot-update.json",
      "publicPath": "/static/dist/main.41a4ecbac3d541d0d30a.hot-update.json"
    },
    "main.f30aaa2f6fd5440f1af0.hot-update.js": {
      "name": "main.f30aaa2f6fd5440f1af0.hot-update.js",
      "path": "/Users/stevehiehn/SignalsAndSorceryWeb/static/dist/main.f30aaa2f6fd5440f1af0.hot-update.js",
      "publicPath": "/static/dist/main.f30aaa2f6fd5440f1af0.hot-update.js"
    },
    "main.f30aaa2f6fd5440f1af0.hot-update.json": {
      "name": "main.f30aaa2f6fd5440f1af0.hot-update.json",
      "path": "/Users/stevehiehn/SignalsAndSorceryWeb/static/dist/main.f30aaa2f6fd5440f1af0.hot-update.json",
      "publicPath": "/static/dist/main.f30aaa2f6fd5440f1af0.hot-update.json"
    }
  },
  "chunks": {
    "main": [
      "main.js",
      "main.f30aaa2f6fd5440f1af0.hot-update.js"
    ]
  },
  "publicPath": "/static/dist/"
}