{
  "status": "done",
  "assets": {
    "main.js": {
      "name": "main.js",
      "path": "/Users/stevehiehn/SignalsAndSorceryWeb/static/dist/main.js",
      "publicPath": "/static/dist/main.js"
    },
    "main.b4f0a2ce53c975607d44.hot-update.js": {
      "name": "main.b4f0a2ce53c975607d44.hot-update.js",
      "path": "/Users/stevehiehn/SignalsAndSorceryWeb/static/dist/main.b4f0a2ce53c975607d44.hot-update.js",
      "publicPath": "/static/dist/main.b4f0a2ce53c975607d44.hot-update.js"
    },
    "main.b4f0a2ce53c975607d44.hot-update.json": {
      "name": "main.b4f0a2ce53c975607d44.hot-update.json",
      "path": "/Users/stevehiehn/SignalsAndSorceryWeb/static/dist/main.b4f0a2ce53c975607d44.hot-update.json",
      "publicPath": "/static/dist/main.b4f0a2ce53c975607d44.hot-update.json"
    },
    "main.d506914813a9b0620d9c.hot-update.js": {
      "name": "main.d506914813a9b0620d9c.hot-update.js",
      "path": "/Users/stevehiehn/SignalsAndSorceryWeb/static/dist/main.d506914813a9b0620d9c.hot-update.js",
      "publicPath": "/static/dist/main.d506914813a9b0620d9c.hot-update.js"
    },
    "main.d506914813a9b0620d9c.hot-update.json": {
      "name": "main.d506914813a9b0620d9c.hot-update.json",
      "path": "/Users/stevehiehn/SignalsAndSorceryWeb/static/dist/main.d506914813a9b0620d9c.hot-update.json",
      "publicPath": "/static/dist/main.d506914813a9b0620d9c.hot-update.json"
    },
    "main.f176ba551e2d0ceda804.hot-update.js": {
      "name": "main.f176ba551e2d0ceda804.hot-update.js",
      "path": "/Users/stevehiehn/SignalsAndSorceryWeb/static/dist/main.f176ba551e2d0ceda804.hot-update.js",
      "publicPath": "/static/dist/main.f176ba551e2d0ceda804.hot-update.js"
    },
    "main.f176ba551e2d0ceda804.hot-update.json": {
      "name": "main.f176ba551e2d0ceda804.hot-update.json",
      "path": "/Users/stevehiehn/SignalsAndSorceryWeb/static/dist/main.f176ba551e2d0ceda804.hot-update.json",
      "publicPath": "/static/dist/main.f176ba551e2d0ceda804.hot-update.json"
    },
    "main.ccd31ac8c5d3269f6d2f.hot-update.js": {
      "name": "main.ccd31ac8c5d3269f6d2f.hot-update.js",
      "path": "/Users/stevehiehn/SignalsAndSorceryWeb/static/dist/main.ccd31ac8c5d3269f6d2f.hot-update.js",
      "publicPath": "/static/dist/main.ccd31ac8c5d3269f6d2f.hot-update.js"
    },
    "main.ccd31ac8c5d3269f6d2f.hot-update.json": {
      "name": "main.ccd31ac8c5d3269f6d2f.hot-update.json",
      "path": "/Users/stevehiehn/SignalsAndSorceryWeb/static/dist/main.ccd31ac8c5d3269f6d2f.hot-update.json",
      "publicPath": "/static/dist/main.ccd31ac8c5d3269f6d2f.hot-update.json"
    },
    "main.809bb801f1f9f5da33ab.hot-update.js": {
      "name": "main.809bb801f1f9f5da33ab.hot-update.js",
      "path": "/Users/stevehiehn/SignalsAndSorceryWeb/static/dist/main.809bb801f1f9f5da33ab.hot-update.js",
      "publicPath": "/static/dist/main.809bb801f1f9f5da33ab.hot-update.js"
    },
    "main.809bb801f1f9f5da33ab.hot-update.json": {
      "name": "main.809bb801f1f9f5da33ab.hot-update.json",
      "path": "/Users/stevehiehn/SignalsAndSorceryWeb/static/dist/main.809bb801f1f9f5da33ab.hot-update.json",
      "publicPath": "/static/dist/main.809bb801f1f9f5da33ab.hot-update.json"
    },
    "main.d5dbade6a3e4ea05cad3.hot-update.js": {
      "name": "main.d5dbade6a3e4ea05cad3.hot-update.js",
      "path": "/Users/stevehiehn/SignalsAndSorceryWeb/static/dist/main.d5dbade6a3e4ea05cad3.hot-update.js",
      "publicPath": "/static/dist/main.d5dbade6a3e4ea05cad3.hot-update.js"
    },
    "main.d5dbade6a3e4ea05cad3.hot-update.json": {
      "name": "main.d5dbade6a3e4ea05cad3.hot-update.json",
      "path": "/Users/stevehiehn/SignalsAndSorceryWeb/static/dist/main.d5dbade6a3e4ea05cad3.hot-update.json",
      "publicPath": "/static/dist/main.d5dbade6a3e4ea05cad3.hot-update.json"
    },
    "main.ef7fa0b0ca564c65cc22.hot-update.js": {
      "name": "main.ef7fa0b0ca564c65cc22.hot-update.js",
      "path": "/Users/stevehiehn/SignalsAndSorceryWeb/static/dist/main.ef7fa0b0ca564c65cc22.hot-update.js",
      "publicPath": "/static/dist/main.ef7fa0b0ca564c65cc22.hot-update.js"
    },
    "main.ef7fa0b0ca564c65cc22.hot-update.json": {
      "name": "main.ef7fa0b0ca564c65cc22.hot-update.json",
      "path": "/Users/stevehiehn/SignalsAndSorceryWeb/static/dist/main.ef7fa0b0ca564c65cc22.hot-update.json",
      "publicPath": "/static/dist/main.ef7fa0b0ca564c65cc22.hot-update.json"
    },
    "main.ff971f665c0d7dd70a8d.hot-update.js": {
      "name": "main.ff971f665c0d7dd70a8d.hot-update.js",
      "path": "/Users/stevehiehn/SignalsAndSorceryWeb/static/dist/main.ff971f665c0d7dd70a8d.hot-update.js",
      "publicPath": "/static/dist/main.ff971f665c0d7dd70a8d.hot-update.js"
    },
    "main.ff971f665c0d7dd70a8d.hot-update.json": {
      "name": "main.ff971f665c0d7dd70a8d.hot-update.json",
      "path": "/Users/stevehiehn/SignalsAndSorceryWeb/static/dist/main.ff971f665c0d7dd70a8d.hot-update.json",
      "publicPath": "/static/dist/main.ff971f665c0d7dd70a8d.hot-update.json"
    },
    "main.137fde3f31a74fa4bf8b.hot-update.js": {
      "name": "main.137fde3f31a74fa4bf8b.hot-update.js",
      "path": "/Users/stevehiehn/SignalsAndSorceryWeb/static/dist/main.137fde3f31a74fa4bf8b.hot-update.js",
      "publicPath": "/static/dist/main.137fde3f31a74fa4bf8b.hot-update.js"
    },
    "main.137fde3f31a74fa4bf8b.hot-update.json": {
      "name": "main.137fde3f31a74fa4bf8b.hot-update.json",
      "path": "/Users/stevehiehn/SignalsAndSorceryWeb/static/dist/main.137fde3f31a74fa4bf8b.hot-update.json",
      "publicPath": "/static/dist/main.137fde3f31a74fa4bf8b.hot-update.json"
    },
    "main.3a11237e62765a181ded.hot-update.js": {
      "name": "main.3a11237e62765a181ded.hot-update.js",
      "path": "/Users/stevehiehn/SignalsAndSorceryWeb/static/dist/main.3a11237e62765a181ded.hot-update.js",
      "publicPath": "/static/dist/main.3a11237e62765a181ded.hot-update.js"
    },
    "main.3a11237e62765a181ded.hot-update.json": {
      "name": "main.3a11237e62765a181ded.hot-update.json",
      "path": "/Users/stevehiehn/SignalsAndSorceryWeb/static/dist/main.3a11237e62765a181ded.hot-update.json",
      "publicPath": "/static/dist/main.3a11237e62765a181ded.hot-update.json"
    },
    "main.582a5e0a5f82541a630b.hot-update.js": {
      "name": "main.582a5e0a5f82541a630b.hot-update.js",
      "path": "/Users/stevehiehn/SignalsAndSorceryWeb/static/dist/main.582a5e0a5f82541a630b.hot-update.js",
      "publicPath": "/static/dist/main.582a5e0a5f82541a630b.hot-update.js"
    },
    "main.582a5e0a5f82541a630b.hot-update.json": {
      "name": "main.582a5e0a5f82541a630b.hot-update.json",
      "path": "/Users/stevehiehn/SignalsAndSorceryWeb/static/dist/main.582a5e0a5f82541a630b.hot-update.json",
      "publicPath": "/static/dist/main.582a5e0a5f82541a630b.hot-update.json"
    }
  },
  "chunks": {
    "main": [
      "main.js",
      "main.582a5e0a5f82541a630b.hot-update.js"
    ]
  },
  "publicPath": "/static/dist/"
}